urdu_digit.py
urdu_digit-0.0.17.dist-info/METADATA
urdu_digit-0.0.17.dist-info/WHEEL
urdu_digit-0.0.17.dist-info/top_level.txt
urdu_digit-0.0.17.dist-info/RECORD
