Metadata-Version: 2.1
Name: urdu_digit
Version: 0.0.17
Summary: Converts English digits to Urdu digits.
Home-page: https://www.techtum.dev/work-urdu-digit-211001.html
Author: siphr
Author-email: pypi@techtum.dev
License: MIT
Project-URL: Bug Tracker, https://github.com/siphr/urdu-digit/issues
Platform: UNKNOWN
Classifier: Programming Language :: Python :: 3
Classifier: License :: OSI Approved :: MIT License
Classifier: Operating System :: OS Independent
Requires-Python: >=3.6
